{
  "_id": "3AOc3P0n9nnVtuudqSRCcy2bKLP",
  "_type": "LandingPage",
  "_index": "a0",
  "_seeded": "/index.json",
  "title": "Welcome to Step 4",
  "blocks": [
    {
      "_id": "3AOc3PkYDL0HioFzIr74NxOmBXX",
      "_index": "a0",
      "_type": "TextBlock",
      "body": [
        {
          "_type": "paragraph",
          "content": [
            {
              "_type": "text",
              "text": "Step 4 builds on step 3 and adds a blog section with nested posts."
            }
          ]
        }
      ]
    },
    {
      "_id": "3Bstep4WeatherSeed000000000",
      "_index": "a1",
      "_type": "WeatherBlock",
      "title": "Current weather",
      "region": "Brussels"
    }
  ],
  "metadata": {
    "title": "",
    "description": "",
    "openGraph": {
      "image": {},
      "title": "",
      "description": ""
    }
  }
}
